{
  "db_name": "PostgreSQL",
  "query": "SELECT pev.key, pev.encrypted_value, pev.nonce\n         FROM app_env_links ael\n         JOIN project_env_variables pev ON pev.id = ael.project_env_id\n         WHERE ael.app_instance_id = $1 AND pev.is_secret = false",
  "describe": {
    "columns": [
      {
        "ordinal": 0,
        "name": "key",
        "type_info": "Varchar"
      },
      {
        "ordinal": 1,
        "name": "encrypted_value",
        "type_info": "Text"
      },
      {
        "ordinal": 2,
        "name": "nonce",
        "type_info": "Varchar"
      }
    ],
    "parameters": {
      "Left": [
        "Uuid"
      ]
    },
    "nullable": [
      false,
      false,
      false
    ]
  },
  "hash": "30f8f9df1057113efb34162c75932f83c4faabe543d5fed7570652dd101fe3cb"
}
